<bill session="114" type="h" number="2646" updated="2015-08-05T04:47:22-04:00">
  <state datetime="2015-06-04">REFERRED</state>
  <status>
    <introduced datetime="2015-06-04"/>
  </status>
  <introduced datetime="2015-06-04"/>
  <titles>
    <title type="short" as="introduced">Helping Families in Mental Health Crisis Act of 2015</title>
    <title type="official" as="introduced">To make available needed psychiatric, psychological, and supportive services for individuals with mental illness and families in mental health crisis, and for other purposes.</title>
  </titles>
  <sponsor id="400285"/>
  <cosponsors>
    <cosponsor id="412500" joined="2015-06-24"/>
    <cosponsor id="412469" joined="2015-07-07"/>
    <cosponsor id="412541" joined="2015-06-19"/>
    <cosponsor id="412404" joined="2015-06-24"/>
    <cosponsor id="412436" joined="2015-07-28"/>
    <cosponsor id="412512" joined="2015-07-08"/>
    <cosponsor id="412250" joined="2015-06-04"/>
    <cosponsor id="412478" joined="2015-07-13"/>
    <cosponsor id="400032" joined="2015-06-23"/>
    <cosponsor id="400033" joined="2015-06-04"/>
    <cosponsor id="400636" joined="2015-07-29"/>
    <cosponsor id="412652" joined="2015-06-04"/>
    <cosponsor id="412539" joined="2015-07-15"/>
    <cosponsor id="400048" joined="2015-07-07"/>
    <cosponsor id="412196" joined="2015-06-04"/>
    <cosponsor id="412427" joined="2015-07-15"/>
    <cosponsor id="400057" joined="2015-06-04"/>
    <cosponsor id="412622" joined="2015-06-19"/>
    <cosponsor id="400068" joined="2015-07-15"/>
    <cosponsor id="412379" joined="2015-07-21"/>
    <cosponsor id="412271" joined="2015-07-27"/>
    <cosponsor id="400077" joined="2015-07-29"/>
    <cosponsor id="412563" joined="2015-07-08"/>
    <cosponsor id="412272" joined="2015-06-08"/>
    <cosponsor id="412651" joined="2015-07-28"/>
    <cosponsor id="412555" joined="2015-06-11"/>
    <cosponsor id="412400" joined="2015-06-24"/>
    <cosponsor id="400657" joined="2015-07-15"/>
    <cosponsor id="412403" joined="2015-06-04"/>
    <cosponsor id="400648" joined="2015-07-28"/>
    <cosponsor id="400108" joined="2015-06-04"/>
    <cosponsor id="412420" joined="2015-06-04"/>
    <cosponsor id="400114" joined="2015-07-14"/>
    <cosponsor id="412488" joined="2015-07-15"/>
    <cosponsor id="400116" joined="2015-06-15"/>
    <cosponsor id="412457" joined="2015-06-04"/>
    <cosponsor id="400646" joined="2015-07-28"/>
    <cosponsor id="412476" joined="2015-07-13"/>
    <cosponsor id="400640" joined="2015-06-12"/>
    <cosponsor id="400141" joined="2015-07-21"/>
    <cosponsor id="412453" joined="2015-07-22"/>
    <cosponsor id="412447" joined="2015-06-04"/>
    <cosponsor id="412278" joined="2015-06-12"/>
    <cosponsor id="412454" joined="2015-06-23"/>
    <cosponsor id="412434" joined="2015-07-29"/>
    <cosponsor id="412444" joined="2015-07-29"/>
    <cosponsor id="400170" joined="2015-06-04"/>
    <cosponsor id="412584" joined="2015-07-31"/>
    <cosponsor id="400179" joined="2015-06-10"/>
    <cosponsor id="412550" joined="2015-06-08"/>
    <cosponsor id="412283" joined="2015-06-04"/>
    <cosponsor id="412561" joined="2015-06-24"/>
    <cosponsor id="412460" joined="2015-07-21"/>
    <cosponsor id="400204" joined="2015-06-04"/>
    <cosponsor id="412566" joined="2015-07-07"/>
    <cosponsor id="400211" joined="2015-07-14"/>
    <cosponsor id="412649" joined="2015-06-10"/>
    <cosponsor id="412465" joined="2015-07-28"/>
    <cosponsor id="412421" joined="2015-07-29"/>
    <cosponsor id="412510" joined="2015-07-08"/>
    <cosponsor id="412290" joined="2015-06-16"/>
    <cosponsor id="412638" joined="2015-07-21"/>
    <cosponsor id="412616" joined="2015-08-04"/>
    <cosponsor id="412521" joined="2015-07-08"/>
    <cosponsor id="400247" joined="2015-07-29"/>
    <cosponsor id="412294" joined="2015-07-29"/>
    <cosponsor id="412487" joined="2015-06-10"/>
    <cosponsor id="412611" joined="2015-06-24"/>
    <cosponsor id="412540" joined="2015-07-29"/>
    <cosponsor id="400273" joined="2015-07-29"/>
    <cosponsor id="400276" joined="2015-06-04"/>
    <cosponsor id="412568" joined="2015-07-08"/>
    <cosponsor id="412475" joined="2015-07-29"/>
    <cosponsor id="408211" joined="2015-07-23"/>
    <cosponsor id="400297" joined="2015-06-04"/>
    <cosponsor id="412302" joined="2015-07-15"/>
    <cosponsor id="412303" joined="2015-07-28"/>
    <cosponsor id="412523" joined="2015-08-04"/>
    <cosponsor id="400316" joined="2015-06-25"/>
    <cosponsor id="412659" joined="2015-07-22"/>
    <cosponsor id="400333" joined="2015-06-16"/>
    <cosponsor id="412394" joined="2015-07-28"/>
    <cosponsor id="412310" joined="2015-06-25"/>
    <cosponsor id="412202" joined="2015-07-15"/>
    <cosponsor id="412570" joined="2015-07-29"/>
    <cosponsor id="400350" joined="2015-06-25"/>
    <cosponsor id="400606" joined="2015-07-27"/>
    <cosponsor id="400365" joined="2015-07-15"/>
    <cosponsor id="409888" joined="2015-07-28"/>
    <cosponsor id="412509" joined="2015-06-04"/>
    <cosponsor id="400380" joined="2015-07-29"/>
    <cosponsor id="412461" joined="2015-07-29"/>
    <cosponsor id="400402" joined="2015-07-07"/>
    <cosponsor id="412317" joined="2015-07-15"/>
    <cosponsor id="412318" joined="2015-07-28"/>
    <cosponsor id="412636" joined="2015-06-19"/>
    <cosponsor id="400411" joined="2015-07-29"/>
    <cosponsor id="412522" joined="2015-06-04"/>
    <cosponsor id="412538" joined="2015-07-29"/>
    <cosponsor id="412618" joined="2015-06-04"/>
    <cosponsor id="412214" joined="2015-07-07"/>
    <cosponsor id="412410" joined="2015-06-19"/>
    <cosponsor id="412564" joined="2015-06-16"/>
    <cosponsor id="400431" joined="2015-06-17"/>
    <cosponsor id="400433" joined="2015-06-24"/>
    <cosponsor id="412526" joined="2015-07-21" withdrawn="2015-07-22"/>
    <cosponsor id="412565" joined="2015-07-21" withdrawn="2015-07-22"/>
    <cosponsor id="400245" joined="2015-07-21" withdrawn="2015-07-22"/>
  </cosponsors>
  <actions>
    <action datetime="2015-06-04" state="REFERRED">
      <text>Referred to the Committee on Energy and Commerce, and in addition to the Committees on Ways and Means, and Education and the Workforce, for a period to be subsequently determined by the Speaker, in each case for consideration of such provisions as fall within the jurisdiction of the committee concerned.</text>
    </action>
    <action datetime="2015-06-04">
      <text>Referred to House Energy and Commerce</text>
    </action>
    <action datetime="2015-06-04">
      <text>Referred to House Ways and Means</text>
    </action>
    <action datetime="2015-06-04">
      <text>Referred to House Education and the Workforce</text>
    </action>
    <action datetime="2015-06-05">
      <text>Referred to the Subcommittee on Health.</text>
    </action>
    <action datetime="2015-06-10">
      <text>Sponsor introductory remarks on measure.</text>
      <reference ref="CR H4008-4009"/>
    </action>
    <action datetime="2015-06-11">
      <text>Sponsor introductory remarks on measure.</text>
      <reference ref="CR H4166-4167"/>
    </action>
    <action datetime="2015-07-09">
      <text>Sponsor introductory remarks on measure.</text>
      <reference ref="CR H4963"/>
    </action>
  </actions>
  <committees>
    <committee code="HSIF" name="House Energy and Commerce" activity="Referral"/>
    <committee activity="Referral" code="HSIF14" subcommittee="Health" name="House Energy and Commerce"/>
    <committee code="HSWM" name="House Ways and Means" activity="Referral"/>
    <committee code="HSED" name="House Education and the Workforce" activity="Referral"/>
  </committees>
  <relatedbills>
    <bill relation="unknown" session="114" type="h" number="938"/>
    <bill relation="unknown" session="114" type="s" number="1299"/>
  </relatedbills>
  <subjects>
    <term name="Health"/>
  </subjects>
  <amendments/>
</bill>
