<bill session="114" type="h" number="2941" updated="2015-07-14T04:48:01-04:00">
  <state datetime="2015-06-25">REFERRED</state>
  <status>
    <introduced datetime="2015-06-25"/>
  </status>
  <introduced datetime="2015-06-25"/>
  <titles>
    <title type="short" as="introduced">Veterans Affairs Employee Accountability Act</title>
    <title type="official" as="introduced">To amend title 38, United States Code, to prohibit the receipt of bonuses by Department of Veterans Affairs employees who violate Federal civil laws or regulations, and for other purposes.</title>
  </titles>
  <sponsor id="412310"/>
  <cosponsors>
    <cosponsor id="412630" joined="2015-07-08"/>
  </cosponsors>
  <actions>
    <action datetime="2015-06-25" state="REFERRED">
      <text>Referred to the House Committee on Veterans' Affairs.</text>
    </action>
    <action datetime="2015-07-10">
      <text>Referred to the Subcommittee on Economic Opportunity.</text>
    </action>
  </actions>
  <committees>
    <committee code="HSVR" name="House Veterans' Affairs" activity="Referral"/>
    <committee activity="Referral" code="HSVR10" subcommittee="Economic Opportunity" name="House Veterans' Affairs"/>
  </committees>
  <relatedbills/>
  <subjects>
    <term name="Armed forces and national security"/>
  </subjects>
  <amendments/>
  <summary>6/25/2015--Introduced.
Veterans Affairs Employee Accountability Act 

 Requires the Department of Veterans Affairs (VA) to ensure that no VA employee who knowingly violates any federal civil law or regulation, including one covered under the Federal Acquisition Regulation or the Veterans Affairs Acquisition Regulation, or any internal VA policy, receives any specified pay augmentation, incentive, or additional gift of any value (bonus).</summary>
</bill>
