<bill session="114" type="h" number="3280" updated="2015-08-08T06:46:44-04:00">
  <state datetime="2015-07-29">REFERRED</state>
  <status>
    <introduced datetime="2015-07-29"/>
  </status>
  <introduced datetime="2015-07-29"/>
  <titles>
    <title type="short" as="introduced">Widening Internet Readiness for Employment Development Act</title>
    <title type="short" as="introduced">WIRED Act</title>
    <title type="official" as="introduced">To amend the Workforce Innovation and Opportunity Act to require one-stop delivery systems under such Act to offer services through Internet websites and to direct the Secretary of Labor to develop standards and best practices for such websites, and other purposes.</title>
  </titles>
  <sponsor id="412514"/>
  <cosponsors>
    <cosponsor id="412550" joined="2015-07-29"/>
    <cosponsor id="412648" joined="2015-07-29"/>
  </cosponsors>
  <actions>
    <action datetime="2015-07-29" state="REFERRED">
      <text>Referred to the House Committee on Education and the Workforce.</text>
    </action>
  </actions>
  <committees>
    <committee code="HSED" name="House Education and the Workforce" activity="Referral"/>
  </committees>
  <relatedbills/>
  <subjects>
    <term name="Labor and employment"/>
  </subjects>
  <amendments/>
</bill>
