<bill session="114" type="s" number="510" updated="2015-03-14T06:41:35-04:00">
  <state datetime="2015-02-12">REFERRED</state>
  <status>
    <introduced datetime="2015-02-12"/>
  </status>
  <introduced datetime="2015-02-12"/>
  <titles>
    <title type="short" as="introduced">Bureau of Consumer Financial Protection-Inspector General Reform Act of 2015</title>
    <title type="short" as="introduced">CFPB-IG Act of 2015</title>
    <title type="official" as="introduced">A bill to require Senate confirmation of Inspector General of the Bureau of Consumer Financial Protection, and for other purposes.</title>
  </titles>
  <sponsor id="400325"/>
  <cosponsors>
    <cosponsor id="412493" joined="2015-02-12"/>
    <cosponsor id="412251" joined="2015-02-12"/>
    <cosponsor id="400034" joined="2015-02-12"/>
    <cosponsor id="400040" joined="2015-02-12"/>
    <cosponsor id="400061" joined="2015-02-12"/>
    <cosponsor id="300023" joined="2015-02-12"/>
    <cosponsor id="300025" joined="2015-02-12"/>
    <cosponsor id="412248" joined="2015-02-12"/>
    <cosponsor id="412508" joined="2015-02-24"/>
    <cosponsor id="300030" joined="2015-02-12"/>
    <cosponsor id="412218" joined="2015-02-12"/>
    <cosponsor id="412494" joined="2015-02-12"/>
    <cosponsor id="400194" joined="2015-02-12"/>
  </cosponsors>
  <actions>
    <action datetime="2015-02-12" state="REFERRED">
      <text>Read twice and referred to the Committee on Banking, Housing, and Urban Affairs.</text>
    </action>
  </actions>
  <committees>
    <committee code="SSBK" name="Senate Banking, Housing, and Urban Affairs" activity="Referral"/>
  </committees>
  <relatedbills>
    <bill relation="unknown" session="114" type="h" number="957"/>
  </relatedbills>
  <subjects>
    <term name="Finance and financial sector"/>
    <term name="Consumer Financial Protection Bureau"/>
    <term name="Executive agency funding and structure"/>
    <term name="Federal officials"/>
    <term name="Government studies and investigations"/>
  </subjects>
  <amendments/>
  <summary>2/12/2015--Introduced.
Bureau of Consumer Financial Protection-Inspector General Reform Act of 2015 or CFPB-IG Act of 2015

 Amends the Inspector General Act of 1978 to repeal the authority of the Chairman of the Board of Governors of the Federal Reserve System to appoint the Inspector General of the Consumer Financial Protection Bureau (CFPB).

Requires the CFPB Inspector General to be appointed by the President, by and with the advice and consent of the Senate.</summary>
</bill>
